pythia_datasets/__init__.py
pythia_datasets/datasets.py
pythia_datasets/registry.txt
pythia_datasets/tests/test_dataset.py
pythia_datasets-2021.9.21.dist-info/LICENSE
pythia_datasets-2021.9.21.dist-info/METADATA
pythia_datasets-2021.9.21.dist-info/WHEEL
pythia_datasets-2021.9.21.dist-info/top_level.txt
pythia_datasets-2021.9.21.dist-info/RECORD
