Metadata-Version: 2.1
Name: pythia-datasets
Version: 2021.9.21
Summary: Provides utility functions for accessing data repository for Project Pythia examples/notebooks
Home-page: https://github.com/ProjectPythia/pythia-datasets
Maintainer: Project Pythia Team
Maintainer-email: 
License: Apache Software License 2.0
Project-URL: Documentation, https://github.com/ProjectPythia/pythia-datasets
Project-URL: Source, https://github.com/ProjectPythia/pythia-datasets
Project-URL: Tracker, https://github.com/ProjectPythia/pythia-datasets/issues
Keywords: Pythia,Pooch
Platform: UNKNOWN
Classifier: Development Status :: 2 - Pre-Alpha
Classifier: License :: OSI Approved :: Apache Software License
Classifier: Natural Language :: English
Classifier: Programming Language :: Python :: 3
Classifier: Programming Language :: Python :: 3.7
Classifier: Programming Language :: Python :: 3.8
Classifier: Programming Language :: Python :: 3.9
Classifier: Topic :: Scientific/Engineering
Classifier: Operating System :: OS Independent
Classifier: Intended Audience :: Science/Research
Requires-Python: >=3.7
License-File: LICENSE
Requires-Dist: pooch
